quotesgeneratorapi_wrapper/__init__.py
quotesgeneratorapi_wrapper/quotesgenerator.py
quotesgeneratorapi_wrapper-2026.1.3.dist-info/METADATA
quotesgeneratorapi_wrapper-2026.1.3.dist-info/WHEEL
quotesgeneratorapi_wrapper-2026.1.3.dist-info/licenses/LICENSE
quotesgeneratorapi_wrapper-2026.1.3.dist-info/RECORD
