Metadata-Version: 2.4
Name: quotesgeneratorapi-wrapper
Version: 2026.1.3
Summary: A wrapper for quotes from API Ninjas
License-Expression: MIT
License-File: LICENSE
Author: tct123
Author-email: 42028373+tct123@users.noreply.github.com
Requires-Python: >=3.14
Classifier: Programming Language :: Python :: 3
Classifier: Programming Language :: Python :: 3.14
Requires-Dist: requests
